rom16x8.v
// -------------------- ROM --------------------
// 16 cells of f8 bit DATA

module rom16x8(
	input [ADDR_WIDTH-1:0] ADDR,
	output reg [WIDTH-1:0] DATA
);

parameter WIDTH = 12;
parameter ADDR_WIDTH = 4;

always @(*) begin
	case(ADDR)
		4'h0: DATA <= 12'hC00; // nop				0	0
		4'h1: DATA <= 12'hD20; // ldi 2			1	0
		// 4'h1: DATA <= 12'h900; // inc A			1	0
		4'h2: DATA <= 12'h900; // inc A			2	0
		4'h3: DATA <= 12'h900; // inc A			3	0
		4'h4: DATA <= 12'hB00; // ST R			3	3
		4'h5: DATA <= 12'h900; // inc A			4	3
		4'h6: DATA <= 12'h900; // inc A			5	3
		4'h7: DATA <= 12'h500; // add R			8	3
		4'h8: DATA <= 12'h900; // inc A			9	3
		4'h9: DATA <= 12'h900; // inc A			A	3
		4'hA: DATA <= 12'hA00; // LD R			3	3
		4'hB: DATA <= 12'h500; // add R			6	3
		4'hC: DATA <= 12'h900; // inc A			7	3
		4'hD: DATA <= 12'h900; // inc A			8	3
		4'hE: DATA <= 12'hE00; // rst				8	3
		4'hF: DATA <= 12'hC00;
	endcase
end

endmodule // rom16x8

mux2.v
// -------------------- MUX --------------------
// good one 2 on one

module mux2(
	input [DATA_WIDTH-1:0] IN0,
	input [DATA_WIDTH-1:0] IN1,
	input SEL,
	output reg [DATA_WIDTH-1:0] OUT
);

parameter DATA_WIDTH = 8;

always @(*) begin
	case(SEL)
		1'b0: OUT <= IN0;
		1'b1: OUT <= IN1;
	endcase
end

endmodule // mux2

register.v
// -------------------- REGISTERS --------------------
// only one

module register(
	input [WIDTH-1:0] IN,
	input CLK,
	input CE,
	// input RST,
	output reg [WIDTH-1:0] OUT
);

parameter WIDTH = 8;

always @(posedge CLK) begin
	// if(RST == 1'b1) OUT <= 1'b0; // needed for sim when there are none ldi instructions
	// else begin
		if(CE == 1'b0) OUT <= OUT;
		else OUT <= IN;
	// end
end

endmodule // register

ALU.v
module alu(
	input [DATA_WIDTH-1:0] IN0,
	input [DATA_WIDTH-1:0] IN1,
	input [OP_WIDTH-1:0] OP,
	output reg [DATA_WIDTH-1:0] OUT
);

parameter DATA_WIDTH = 8;
parameter OP_WIDTH = 4;

always @(*) begin
	case(OP)
		4'b0000: OUT <= ~IN0;			// NOT
		4'b0001: OUT <= IN0 ^ IN1;		// XOR
		4'b0010: OUT <= IN0 | IN1;		// OR
		4'b0011: OUT <= IN0 & IN1;		// AND
		4'b0100: OUT <= IN0 - IN1;		// SUB
		4'b0101: OUT <= IN0 + IN1;		// ADD
		4'b0110: OUT <= IN0 >> 1;		// RR
		4'b0111: OUT <= IN0 << 1;		// RL
		4'b1000: OUT <= IN0 - 1'b1;		// DEC
		4'b1001: OUT <= IN0 + 1'b1;		// INC
		4'b1010: OUT <= IN0;			// IN0
		4'b1011: OUT <= IN1;			// IN1
		default: OUT <= IN0;
	endcase
end

endmodule // alu

instruction_decoder.v
// -------------------- INSTRUCTION DECODER --------------------
// idk mb i aint good at this, need mo booze

module instruction_decoder(
	input [INSTR_WIDTH-1:0] INSTRUCTION,
	output reg RESET_INSTR,
	output reg SEL,
	output reg CE_R0,
	output reg CE_ACC,
	output reg [OP_WIDTH-1:0] OP
);

parameter INSTR_WIDTH = 4;
parameter OP_WIDTH = 4;

always @(*) begin
	case(INSTRUCTION)
	//					RESET SEL CE(reg) CE(acc) inst1 inst0
		4'h0: {RESET_INSTR, SEL, CE_R0, CE_ACC, OP[OP_WIDTH-1:0]} <= 8'b00010000; // NOT
		4'h1: {RESET_INSTR, SEL, CE_R0, CE_ACC, OP[OP_WIDTH-1:0]} <= 8'b00010001; // XOR
		4'h2: {RESET_INSTR, SEL, CE_R0, CE_ACC, OP[OP_WIDTH-1:0]} <= 8'b00010010; // OR
		4'h3: {RESET_INSTR, SEL, CE_R0, CE_ACC, OP[OP_WIDTH-1:0]} <= 8'b00010011; // AND
		4'h4: {RESET_INSTR, SEL, CE_R0, CE_ACC, OP[OP_WIDTH-1:0]} <= 8'b00010100; // SUB
		4'h5: {RESET_INSTR, SEL, CE_R0, CE_ACC, OP[OP_WIDTH-1:0]} <= 8'b00010101; // ADD R
		4'h6: {RESET_INSTR, SEL, CE_R0, CE_ACC, OP[OP_WIDTH-1:0]} <= 8'b00010110; // RR
		4'h7: {RESET_INSTR, SEL, CE_R0, CE_ACC, OP[OP_WIDTH-1:0]} <= 8'b00010111; // RL
		4'h8: {RESET_INSTR, SEL, CE_R0, CE_ACC, OP[OP_WIDTH-1:0]} <= 8'b00011000; // DEC
		4'h9: {RESET_INSTR, SEL, CE_R0, CE_ACC, OP[OP_WIDTH-1:0]} <= 8'b00011001; // INC
		4'hA: {RESET_INSTR, SEL, CE_R0, CE_ACC, OP[OP_WIDTH-1:0]} <= 8'b00011011; // LD R
		4'hB: {RESET_INSTR, SEL, CE_R0, CE_ACC, OP[OP_WIDTH-1:0]} <= 8'b00101010; // ST R
		4'hC: {RESET_INSTR, SEL, CE_R0, CE_ACC, OP[OP_WIDTH-1:0]} <= 8'b00001010; // NOP
		4'hD: {RESET_INSTR, SEL, CE_R0, CE_ACC, OP[OP_WIDTH-1:0]} <= 8'b01011010; // LDI
		4'hE: {RESET_INSTR, SEL, CE_R0, CE_ACC, OP[OP_WIDTH-1:0]} <= 8'b10001010; // RST
		4'hF: {RESET_INSTR, SEL, CE_R0, CE_ACC, OP[OP_WIDTH-1:0]} <= 8'b10001010; // RST
	endcase
end

endmodule // instruction_decoder

memory.v
module memory(
    input [ADDR_WIDTH-1:0] ADDR,
	output reg [WIDTH-1:0] DATA
);

parameter ADDR_WIDTH = 4;
parameter WIDTH = 12;

reg [WIDTH-1:0] MEM [0:(2**ADDR_WIDTH)-1];

always @(ADDR) DATA <= MEM[ADDR];

initial begin
    $readmemb("rom_test.mem", MEM);
end

endmodule // memory

program_counter.v
// -------------------- COUNTER --------------------
// counter module of WIDTH bits width

module program_counter(
	input RST,
	input CLK,
	output reg [WIDTH-1:0] DATA
);

parameter WIDTH = 4;

always @(posedge CLK) begin
	if(RST == 1) DATA <= 4'h0;
	else DATA <= DATA + 1;
end

endmodule // program_counter

tb_processor.v
`timescale 1ns/100ps
`include "program_counter.v"
`include "rom16x8.v"
`include "instruction_decoder.v"
`include "alu.v"
`include "register.v"
`include "mux2.v"
`include "memory.v"

module tb_processor();

parameter DATA_WIDTH = 8;
parameter OP_WIDTH = 4;
parameter PC_WIDTH = 4;
parameter ROM_WIDTH = 12;

reg RESET;
reg CLK;
wire [PC_WIDTH-1:0] TO_ROM;
wire [ROM_WIDTH-1:0] TO_ID;
wire RST_CODE;
wire MUX_SEL;
wire CE_R0;
wire CE_ACC;
wire [OP_WIDTH-1:0] OP;
wire [DATA_WIDTH-1:0] ACC_OUT;
wire [DATA_WIDTH-1:0] R0_OUT;
wire [DATA_WIDTH-1:0] ALU_OUT;
wire [DATA_WIDTH-1:0] MUX_OUT;

program_counter p1(
    .RST(RESET | RST_CODE),
    .CLK(CLK),
    .DATA(TO_ROM)
);

// rom16x8 ROM(
//     .ADDR(TO_ROM),
//     .DATA(TO_ID)
// );

memory mem(
    .ADDR(TO_ROM),
    .DATA(TO_ID)
);

instruction_decoder ID(
    .INSTRUCTION(TO_ID[11:8]),
    .RESET_INSTR(RST_CODE),
    .SEL(MUX_SEL),
    .CE_R0(CE_R0),
    .CE_ACC(CE_ACC),
    .OP(OP)
);

alu ALU(
    .IN0(MUX_OUT),
    .IN1(R0_OUT),
    .OP(OP),
    .OUT(ALU_OUT)
);

register ACC(
    .IN(ALU_OUT),
    .CLK(CLK),
    .CE(CE_ACC),
    // .RST(RESET),
    .OUT(ACC_OUT)
);

register R0(
    .IN(ACC_OUT),
    .CLK(CLK),
    .CE(CE_R0),
    // .RST(RESET),
    .OUT(R0_OUT)
);

mux2 mux_alu(
    .IN0(ACC_OUT),
    .IN1(TO_ID[7:0]),
    .SEL(MUX_SEL),
    .OUT(MUX_OUT)
);

initial begin // clock generation
    CLK = 1'b0;
    forever #5 CLK = ~CLK;
end

initial begin // start conditions
    RESET = 1'b1;
end

initial begin // testbench program
    #10 RESET = 1'b0;

    #200 $finish;
end

initial begin
    $dumpfile("tb_processor.vcd");
    $dumpvars(0, tb_processor);
    $dumpon;
end

endmodule

tb_processor.vcd
$date
	Thu Nov 02 17:18:57 2023
$end
$version
	Icarus Verilog
$end
$timescale
	100ps
$end
$scope module tb_processor $end
$var wire 8 ! ACC_OUT [7:0] $end
$var wire 8 " ALU_OUT [7:0] $end
$var wire 1 # CE_ACC $end
$var wire 1 $ CE_R0 $end
$var wire 8 % MUX_OUT [7:0] $end
$var wire 1 & MUX_SEL $end
$var wire 4 ' OP [3:0] $end
$var wire 8 ( R0_OUT [7:0] $end
$var wire 1 ) RST_CODE $end
$var wire 12 * TO_ID [11:0] $end
$var wire 4 + TO_ROM [3:0] $end
$var reg 1 , CLK $end
$var reg 1 - RESET $end
$scope module p1 $end
$var wire 1 . CLK $end
$var wire 1 / RST $end
$var reg 4 0 DATA [3:0] $end
$upscope $end
$scope module mem $end
$var wire 4 1 ADDR [3:0] $end
$var reg 12 2 DATA [11:0] $end
$upscope $end
$scope module ID $end
$var wire 4 3 INSTRUCTION [3:0] $end
$var reg 1 4 CE_ACC $end
$var reg 1 5 CE_R0 $end
$var reg 4 6 OP [3:0] $end
$var reg 1 7 RESET_INSTR $end
$var reg 1 8 SEL $end
$upscope $end
$scope module ALU $end
$var wire 8 9 IN0 [7:0] $end
$var wire 8 : IN1 [7:0] $end
$var wire 4 ; OP [3:0] $end
$var reg 8 < OUT [7:0] $end
$upscope $end
$scope module ACC $end
$var wire 1 # CE $end
$var wire 1 . CLK $end
$var wire 8 = IN [7:0] $end
$var reg 8 > OUT [7:0] $end
$upscope $end
$scope module R0 $end
$var wire 1 $ CE $end
$var wire 1 . CLK $end
$var wire 8 ? IN [7:0] $end
$var reg 8 @ OUT [7:0] $end
$upscope $end
$scope module mux_alu $end
$var wire 8 A IN0 [7:0] $end
$var wire 8 B IN1 [7:0] $end
$var wire 1 & SEL $end
$var reg 8 C OUT [7:0] $end
$upscope $end
$upscope $end
$enddefinitions $end
#0
$dumpvars
bx C
bx B
bx A
bx @
bx ?
bx >
bx =
bx <
bx ;
bx :
bx 9
x8
x7
bx 6
x5
x4
bx 3
bx 2
bx 1
bx 0
1/
0.
1-
0,
bx +
bx *
x)
bx (
bx '
x&
bx %
x$
x#
bx "
bx !
$end
#50
b1101010 <
b1101010 "
b1101010 =
b1101010 C
b1101010 %
b1101010 9
07
0)
18
1&
05
0$
14
1#
b1010 6
b1010 '
b1010 ;
b1101010 B
b1101 3
b110101101010 2
b110101101010 *
b0 0
b0 +
b0 1
1,
1.
#100
0/
0,
0.
0-
#150
b1101010 <
b1101010 "
b1101010 =
b1101010 C
b1101010 %
b1101010 9
08
0&
15
1$
04
0#
b0 B
b1011 3
b101100000000 2
b101100000000 *
b1101010 >
b1101010 !
b1101010 ?
b1101010 A
b1 0
b1 +
b1 1
1,
1.
#200
0,
0.
#250
b110100 <
b110100 "
b110100 =
b110100 C
b110100 %
b110100 9
18
1&
05
0$
14
1#
b110100 B
b1101 3
b110100110100 2
b110100110100 *
b10 0
b10 +
b10 1
b1101010 @
b1101010 (
b1101010 :
1,
1.
#300
0,
0.
#350
b1111110 <
b1111110 "
b1111110 =
b110100 C
b110100 %
b110100 9
08
0&
b10 6
b10 '
b10 ;
b0 B
b10 3
b1000000000 2
b1000000000 *
b110100 >
b110100 !
b110100 ?
b110100 A
b11 0
b11 +
b11 1
1,
1.
#400
0,
0.
#450
b11101000 <
b11101000 "
b11101000 =
b101 6
b101 '
b101 ;
b101 3
b10100000000 2
b10100000000 *
b1111110 C
b1111110 %
b1111110 9
b100 0
b100 +
b100 1
b1111110 >
b1111110 !
b1111110 ?
b1111110 A
1,
1.
#500
0,
0.
#550
b11 6
b11 '
b11 ;
b1101000 <
b1101000 "
b1101000 =
b11 3
b11101000 C
b11101000 %
b11101000 9
b1100000000 2
b1100000000 *
b11101000 >
b11101000 !
b11101000 ?
b11101000 A
b101 0
b101 +
b101 1
1,
1.
#600
0,
0.
#650
b10 <
b10 "
b10 =
b1 6
b1 '
b1 ;
b1 3
b100000000 2
b100000000 *
b1101000 C
b1101000 %
b1101000 9
b110 0
b110 +
b110 1
b1101000 >
b1101000 !
b1101000 ?
b1101000 A
1,
1.
#700
0,
0.
#750
04
0#
b1010 6
b1010 '
b1010 ;
b10 <
b10 "
b10 =
b1100 3
b10 C
b10 %
b10 9
b110000000000 2
b110000000000 *
b10 >
b10 !
b10 ?
b10 A
b111 0
b111 +
b111 1
1,
1.
#800
0,
0.
#850
b1000 0
b1000 +
b1000 1
1,
1.
#900
0,
0.
#950
15
1$
b1011 3
b101100000000 2
b101100000000 *
b1001 0
b1001 +
b1001 1
1,
1.
#1000
0,
0.
#1050
b1111 <
b1111 "
b1111 =
b1111 C
b1111 %
b1111 9
18
1&
05
0$
14
1#
b1111 B
b1101 3
b110100001111 2
b110100001111 *
b1010 0
b1010 +
b1010 1
b10 @
b10 (
b10 :
1,
1.
#1100
0,
0.
#1150
b1101 <
b1101 "
b1101 =
b1111 C
b1111 %
b1111 9
08
0&
b100 6
b100 '
b100 ;
b0 B
b100 3
b10000000000 2
b10000000000 *
b1111 >
b1111 !
b1111 ?
b1111 A
b1011 0
b1011 +
b1011 1
1,
1.
#1200
0,
0.
#1250
1/
17
1)
04
0#
b1010 6
b1010 '
b1010 ;
b1101 <
b1101 "
b1101 =
b1111 3
b111100000000 2
b111100000000 *
b1101 C
b1101 %
b1101 9
b1100 0
b1100 +
b1100 1
b1101 >
b1101 !
b1101 ?
b1101 A
1,
1.
#1300
0,
0.
#1350
b1101010 <
b1101010 "
b1101010 =
b1101010 C
b1101010 %
b1101010 9
0/
07
0)
18
1&
14
1#
b1101010 B
b1101 3
b110101101010 2
b110101101010 *
b0 0
b0 +
b0 1
1,
1.
#1400
0,
0.
#1450
b1101010 <
b1101010 "
b1101010 =
b1101010 C
b1101010 %
b1101010 9
08
0&
15
1$
04
0#
b0 B
b1011 3
b101100000000 2
b101100000000 *
b1 0
b1 +
b1 1
b1101010 >
b1101010 !
b1101010 ?
b1101010 A
1,
1.
#1500
0,
0.
#1550
b110100 <
b110100 "
b110100 =
b110100 C
b110100 %
b110100 9
18
1&
05
0$
14
1#
b110100 B
b1101 3
b110100110100 2
b110100110100 *
b1101010 @
b1101010 (
b1101010 :
b10 0
b10 +
b10 1
1,
1.
#1600
0,
0.
#1650
b1111110 <
b1111110 "
b1111110 =
b110100 C
b110100 %
b110100 9
08
0&
b10 6
b10 '
b10 ;
b0 B
b10 3
b1000000000 2
b1000000000 *
b11 0
b11 +
b11 1
b110100 >
b110100 !
b110100 ?
b110100 A
1,
1.
#1700
0,
0.
#1750
b11101000 <
b11101000 "
b11101000 =
b101 6
b101 '
b101 ;
b101 3
b1111110 C
b1111110 %
b1111110 9
b10100000000 2
b10100000000 *
b1111110 >
b1111110 !
b1111110 ?
b1111110 A
b100 0
b100 +
b100 1
1,
1.
#1800
0,
0.
#1850
b11 6
b11 '
b11 ;
b1101000 <
b1101000 "
b1101000 =
b11 3
b1100000000 2
b1100000000 *
b11101000 C
b11101000 %
b11101000 9
b101 0
b101 +
b101 1
b11101000 >
b11101000 !
b11101000 ?
b11101000 A
1,
1.
#1900
0,
0.
#1950
b10 <
b10 "
b10 =
b1 6
b1 '
b1 ;
b1 3
b1101000 C
b1101000 %
b1101000 9
b100000000 2
b100000000 *
b1101000 >
b1101000 !
b1101000 ?
b1101000 A
b110 0
b110 +
b110 1
1,
1.
#2000
0,
0.
#2050
04
0#
b1010 6
b1010 '
b1010 ;
b10 <
b10 "
b10 =
b1100 3
b110000000000 2
b110000000000 *
b10 C
b10 %
b10 9
b111 0
b111 +
b111 1
b10 >
b10 !
b10 ?
b10 A
1,
1.
