mux.v
// -------------------- MUX --------------------
// good one 2 on one

module mux2(
	input [DATA_WIDTH-1:0] IN0,
	input [DATA_WIDTH-1:0] IN1,
	input SEL,
	output [DATA_WIDTH-1:0] OUT
);

parameter DATA_WIDTH = 4;

reg [3:0] OUT;

always @(*) begin
	case(SEL)
		1'b0: OUT <= IN0;
		1'b1: OUT <= IN1;
	endcase
end

endmodule // mux2

register.v
// -------------------- REGISTERS --------------------
// only one

module register(
	input [WIDTH-1:0] IN,
	input CLK,
	input CE,
	// input RST,
	output [WIDTH-1:0] OUT
);

parameter WIDTH = 4;

reg [WIDTH-1:0] OUT;

always @(posedge CLK) begin
	// if(RST == 1'b1) OUT <= 1'b0; // needed for sim when there are none ldi instructions
	// else begin
		if(CE == 1'b0) OUT <= OUT;
		else OUT <= IN;
	// end
end

endmodule // register

ALU.v
module alu(
	input [DATA_WIDTH-1:0] IN0,
	input [DATA_WIDTH-1:0] IN1,
	input [OP_WIDTH-1:0] OP,
	output [DATA_WIDTH-1:0] OUT
);

parameter DATA_WIDTH = 4;
parameter OP_WIDTH = 2;

reg [DATA_WIDTH-1:0] OUT;

always @(*) begin
	case(OP)
		2'b00: OUT <= IN0 + IN1;		// SUM
		2'b01: OUT <= IN0;				// IN0
		2'b10: OUT <= IN0 + 1'b1;		// INC IN0
		2'b11: OUT <= IN1;				// IN1
	endcase
end

endmodule // alu

instruction_decoder.v
// -------------------- INSTRUCTION DECODER --------------------
// idk mb i aint good at this, need mo booze

module instruction_decoder(
	input [INSTR_WIDTH-1:0] INSTRUCTION,
	output RESET_INSTR,
	output SEL,
	output CE_R0,
	output CE_ACC,
	output [OP_WIDTH-1:0] OP
);

parameter INSTR_WIDTH = 4;
parameter OP_WIDTH = 2;

reg RESET_INSTR;
reg SEL;
reg CE_R0;
reg CE_ACC;
reg [OP_WIDTH-1:0] OP;

always @(*) begin
	case(INSTRUCTION)
	//					RESET SEL CE(reg) CE(acc) inst1 inst0
		4'h0: {RESET_INSTR, SEL, CE_R0, CE_ACC, OP[OP_WIDTH-1:0]} <= 6'b000001; // -NOT
		4'h1: {RESET_INSTR, SEL, CE_R0, CE_ACC, OP[OP_WIDTH-1:0]} <= 6'b000010; // -XOR
		4'h2: {RESET_INSTR, SEL, CE_R0, CE_ACC, OP[OP_WIDTH-1:0]} <= 6'b000011; // -OR
		4'h3: {RESET_INSTR, SEL, CE_R0, CE_ACC, OP[OP_WIDTH-1:0]} <= 6'b000100; // -AND
		4'h4: {RESET_INSTR, SEL, CE_R0, CE_ACC, OP[OP_WIDTH-1:0]} <= 6'b000101; // -SUB
		4'h5: {RESET_INSTR, SEL, CE_R0, CE_ACC, OP[OP_WIDTH-1:0]} <= 6'b000100; // ADD R
		4'h6: {RESET_INSTR, SEL, CE_R0, CE_ACC, OP[OP_WIDTH-1:0]} <= 6'b000111; // -RR
		4'h7: {RESET_INSTR, SEL, CE_R0, CE_ACC, OP[OP_WIDTH-1:0]} <= 6'b001000; // -RL
		4'h8: {RESET_INSTR, SEL, CE_R0, CE_ACC, OP[OP_WIDTH-1:0]} <= 6'b001001; // -DEC
		4'h9: {RESET_INSTR, SEL, CE_R0, CE_ACC, OP[OP_WIDTH-1:0]} <= 6'b000110; // INC
		4'hA: {RESET_INSTR, SEL, CE_R0, CE_ACC, OP[OP_WIDTH-1:0]} <= 6'b000111; // LD
		4'hB: {RESET_INSTR, SEL, CE_R0, CE_ACC, OP[OP_WIDTH-1:0]} <= 6'b001001; // ST
		4'hC: {RESET_INSTR, SEL, CE_R0, CE_ACC, OP[OP_WIDTH-1:0]} <= 6'b000010; // NOP
		4'hD: {RESET_INSTR, SEL, CE_R0, CE_ACC, OP[OP_WIDTH-1:0]} <= 6'b010101; // LDI
		4'hE: {RESET_INSTR, SEL, CE_R0, CE_ACC, OP[OP_WIDTH-1:0]} <= 6'b100010; // RST
		4'hF: {RESET_INSTR, SEL, CE_R0, CE_ACC, OP[OP_WIDTH-1:0]} <= 6'b100010; // RST
	endcase
end

endmodule // instruction_decoder

rom.v
// -------------------- ROM --------------------
// 16 cells of f8 bit DATA

module rom16x8(
	input [ADDR_WIDTH-1:0] ADDR,
	output [WIDTH-1:0] DATA
);

parameter WIDTH = 8;
parameter ADDR_WIDTH = 4;

reg [WIDTH-1:0] DATA;

always @(*) begin
	case(ADDR)
		4'h0: DATA <= 8'hC0; // nop				0	0
		4'h1: DATA <= 8'hD2; // ldi 2			1	0
		// 4'h1: DATA <= 8'h90; // inc A			1	0
		4'h2: DATA <= 8'h90; // inc A			2	0
		4'h3: DATA <= 8'h90; // inc A			3	0
		4'h4: DATA <= 8'hB0; // ST R			3	3
		4'h5: DATA <= 8'h90; // inc A			4	3
		4'h6: DATA <= 8'h90; // inc A			5	3
		4'h7: DATA <= 8'h50; // add R			8	3
		4'h8: DATA <= 8'h90; // inc A			9	3
		4'h9: DATA <= 8'h90; // inc A			A	3
		4'hA: DATA <= 8'hA0; // LD R			3	3
		4'hB: DATA <= 8'h50; // add R			6	3
		4'hC: DATA <= 8'h90; // inc A			7	3
		4'hD: DATA <= 8'h90; // inc A			8	3
		4'hE: DATA <= 8'hE0; // rst				8	3
		4'hF: DATA <= 8'hC0;
	endcase
end

endmodule // rom16x8

program_counter.v
// -------------------- COUNTER --------------------
// counter module of WIDTH bits width

module program_counter(
	input RST,
	input CLK,
	output [WIDTH-1:0] DATA
);

parameter WIDTH = 4;

reg [WIDTH-1:0] DATA;

always @(posedge CLK) begin
	if(RST == 1) DATA <= 4'h0;
	else DATA <= DATA + 1;
end

endmodule // program_counter

tb_processor.v
`timescale 1ns/100ps
`include "program_counter.v"
`include "rom.v"
`include "instruction_decoder.v"
`include "ALU.v"
`include "register.v"
`include "mux.v"

module tb_processor();

parameter DATA_WIDTH = 4;
parameter OP_WIDTH = 2;
parameter PC_WIDTH = 4;
parameter ROM_WIDTH = 8;

reg RESET;
reg CLK;
wire [PC_WIDTH-1:0] TO_ROM;
wire [ROM_WIDTH-1:0] TO_ID;
wire RST_CODE;
wire MUX_SEL;
wire CE_R0;
wire CE_ACC;
wire [OP_WIDTH-1:0] OP;
wire [DATA_WIDTH-1:0] ACC_OUT;
wire [DATA_WIDTH-1:0] R0_OUT;
wire [DATA_WIDTH-1:0] ALU_OUT;
wire [DATA_WIDTH-1:0] MUX_OUT;

program_counter p1(
    .RST(RESET | RST_CODE),
    .CLK(CLK),
    .DATA(TO_ROM)
);

rom16x8 ROM(
    .ADDR(TO_ROM),
    .DATA(TO_ID)
);

instruction_decoder ID(
    .INSTRUCTION(TO_ID[7:4]),
    .RESET_INSTR(RST_CODE),
    .SEL(MUX_SEL),
    .CE_R0(CE_R0),
    .CE_ACC(CE_ACC),
    .OP(OP)
);

alu ALU(
    .IN0(MUX_OUT),
    .IN1(R0_OUT),
    .OP(OP),
    .OUT(ALU_OUT)
);

register ACC(
    .IN(ALU_OUT),
    .CLK(CLK),
    .CE(CE_ACC),
    // .RST(RESET),
    .OUT(ACC_OUT)
);

register R0(
    .IN(ACC_OUT),
    .CLK(CLK),
    .CE(CE_R0),
    // .RST(RESET),
    .OUT(R0_OUT)
);

mux2 mux_alu(
    .IN0(ACC_OUT),
    .IN1(TO_ID[3:0]),
    .SEL(MUX_SEL),
    .OUT(MUX_OUT)
);

initial begin // clock generation
    CLK = 1'b0;
    forever #5 CLK = ~CLK;
end

initial begin // start conditions
    RESET = 1'b1;
end

initial begin // testbench program
    #20 RESET = 1'b0;

    #200 $finish;
end

initial begin
    $dumpfile("tb_processor.vcd");
    $dumpvars(0, tb_processor);
    $dumpon;
end

endmodule

tb_processor.vcd
$date
	Mon Oct 30 09:42:51 2023
$end
$version
	Icarus Verilog
$end
$timescale
	100ps
$end
$scope module tb_processor $end
$var wire 4 ! ACC_OUT [3:0] $end
$var wire 4 " ALU_OUT [3:0] $end
$var wire 1 # CE_ACC $end
$var wire 1 $ CE_R0 $end
$var wire 4 % MUX_OUT [3:0] $end
$var wire 1 & MUX_SEL $end
$var wire 2 ' OP [1:0] $end
$var wire 4 ( R0_OUT [3:0] $end
$var wire 1 ) RST_CODE $end
$var wire 8 * TO_ID [7:0] $end
$var wire 4 + TO_ROM [3:0] $end
$var reg 1 , CLK $end
$var reg 1 - RESET $end
$scope module p1 $end
$var wire 1 . CLK $end
$var wire 1 / RST $end
$var reg 4 0 DATA [3:0] $end
$upscope $end
$scope module ROM $end
$var wire 4 1 ADDR [3:0] $end
$var reg 8 2 DATA [7:0] $end
$upscope $end
$scope module ID $end
$var wire 4 3 INSTRUCTION [3:0] $end
$var reg 1 4 CE_ACC $end
$var reg 1 5 CE_R0 $end
$var reg 2 6 OP [1:0] $end
$var reg 1 7 RESET_INSTR $end
$var reg 1 8 SEL $end
$upscope $end
$scope module ALU $end
$var wire 4 9 IN0 [3:0] $end
$var wire 4 : IN1 [3:0] $end
$var wire 2 ; OP [1:0] $end
$var reg 4 < OUT [3:0] $end
$upscope $end
$scope module ACC $end
$var wire 1 # CE $end
$var wire 1 . CLK $end
$var wire 4 = IN [3:0] $end
$var reg 4 > OUT [3:0] $end
$upscope $end
$scope module R0 $end
$var wire 1 $ CE $end
$var wire 1 . CLK $end
$var wire 4 ? IN [3:0] $end
$var reg 4 @ OUT [3:0] $end
$upscope $end
$scope module mux_alu $end
$var wire 4 A IN0 [3:0] $end
$var wire 4 B IN1 [3:0] $end
$var wire 1 & SEL $end
$var reg 4 C OUT [3:0] $end
$upscope $end
$upscope $end
$enddefinitions $end
#0
$dumpvars
bx C
bx B
bx A
bx @
bx ?
bx >
bx =
bx <
bx ;
bx :
bx 9
x8
x7
bx 6
x5
x4
bx 3
bx 2
bx 1
bx 0
1/
0.
1-
0,
bx +
bx *
x)
bx (
bx '
x&
bx %
x$
x#
bx "
bx !
$end
#50
07
0)
08
0&
05
0$
04
0#
b10 6
b10 '
b10 ;
b0 B
b1100 3
b11000000 2
b11000000 *
b0 0
b0 +
b0 1
1,
1.
#100
0,
0.
#150
1,
1.
#200
0/
0,
0.
0-
#250
b10 <
b10 "
b10 =
b10 C
b10 %
b10 9
18
1&
14
1#
b1 6
b1 '
b1 ;
b10 B
b1101 3
b11010010 2
b11010010 *
b1 0
b1 +
b1 1
1,
1.
#300
0,
0.
#350
b11 <
b11 "
b11 =
b10 C
b10 %
b10 9
08
0&
b10 6
b10 '
b10 ;
b0 B
b1001 3
b10010000 2
b10010000 *
b10 >
b10 !
b10 ?
b10 A
b10 0
b10 +
b10 1
1,
1.
#400
0,
0.
#450
b100 <
b100 "
b100 =
b11 C
b11 %
b11 9
b11 0
b11 +
b11 1
b11 >
b11 !
b11 ?
b11 A
1,
1.
#500
0,
0.
#550
15
1$
04
0#
b1 6
b1 '
b1 ;
b100 <
b100 "
b100 =
b1011 3
b100 C
b100 %
b100 9
b10110000 2
b10110000 *
b100 >
b100 !
b100 ?
b100 A
b100 0
b100 +
b100 1
1,
1.
#600
0,
0.
#650
b101 <
b101 "
b101 =
05
0$
14
1#
b10 6
b10 '
b10 ;
b1001 3
b10010000 2
b10010000 *
b101 0
b101 +
b101 1
b100 @
b100 (
b100 :
1,
1.
#700
0,
0.
#750
b110 <
b110 "
b110 =
b101 C
b101 %
b101 9
b101 >
b101 !
b101 ?
b101 A
b110 0
b110 +
b110 1
1,
1.
#800
0,
0.
#850
b0 6
b0 '
b0 ;
b1010 <
b1010 "
b1010 =
b101 3
b1010000 2
b1010000 *
b110 C
b110 %
b110 9
b111 0
b111 +
b111 1
b110 >
b110 !
b110 ?
b110 A
1,
1.
#900
0,
0.
#950
b10 6
b10 '
b10 ;
b1011 <
b1011 "
b1011 =
b1001 3
b1010 C
b1010 %
b1010 9
b10010000 2
b10010000 *
b1010 >
b1010 !
b1010 ?
b1010 A
b1000 0
b1000 +
b1000 1
1,
1.
#1000
0,
0.
#1050
b1100 <
b1100 "
b1100 =
b1011 C
b1011 %
b1011 9
b1001 0
b1001 +
b1001 1
b1011 >
b1011 !
b1011 ?
b1011 A
1,
1.
#1100
0,
0.
#1150
b11 6
b11 '
b11 ;
b100 <
b100 "
b100 =
b1010 3
b1100 C
b1100 %
b1100 9
b10100000 2
b10100000 *
b1100 >
b1100 !
b1100 ?
b1100 A
b1010 0
b1010 +
b1010 1
1,
1.
#1200
0,
0.
#1250
b1000 <
b1000 "
b1000 =
b0 6
b0 '
b0 ;
b101 3
b1010000 2
b1010000 *
b100 C
b100 %
b100 9
b1011 0
b1011 +
b1011 1
b100 >
b100 !
b100 ?
b100 A
1,
1.
#1300
0,
0.
#1350
b10 6
b10 '
b10 ;
b1001 <
b1001 "
b1001 =
b1001 3
b1000 C
b1000 %
b1000 9
b10010000 2
b10010000 *
b1000 >
b1000 !
b1000 ?
b1000 A
b1100 0
b1100 +
b1100 1
1,
1.
#1400
0,
0.
#1450
b1010 <
b1010 "
b1010 =
b1001 C
b1001 %
b1001 9
b1101 0
b1101 +
b1101 1
b1001 >
b1001 !
b1001 ?
b1001 A
1,
1.
#1500
0,
0.
#1550
1/
17
1)
04
0#
b1011 <
b1011 "
b1011 =
b1110 3
b1010 C
b1010 %
b1010 9
b11100000 2
b11100000 *
b1010 >
b1010 !
b1010 ?
b1010 A
b1110 0
b1110 +
b1110 1
1,
1.
#1600
0,
0.
#1650
0/
07
0)
b1100 3
b11000000 2
b11000000 *
b0 0
b0 +
b0 1
1,
1.
#1700
0,
0.
#1750
b10 C
b10 %
b10 9
b10 <
b10 "
b10 =
18
1&
14
1#
b1 6
b1 '
b1 ;
b10 B
b1101 3
b11010010 2
b11010010 *
b1 0
b1 +
b1 1
1,
1.
#1800
0,
0.
#1850
b11 <
b11 "
b11 =
b10 C
b10 %
b10 9
08
0&
b10 6
b10 '
b10 ;
b0 B
b1001 3
b10010000 2
b10010000 *
b10 0
b10 +
b10 1
b10 >
b10 !
b10 ?
b10 A
1,
1.
#1900
0,
0.
#1950
b100 <
b100 "
b100 =
b11 C
b11 %
b11 9
b11 >
b11 !
b11 ?
b11 A
b11 0
b11 +
b11 1
1,
1.
#2000
0,
0.
#2050
15
1$
04
0#
b1 6
b1 '
b1 ;
b100 <
b100 "
b100 =
b1011 3
b10110000 2
b10110000 *
b100 C
b100 %
b100 9
b100 0
b100 +
b100 1
b100 >
b100 !
b100 ?
b100 A
1,
1.
#2100
0,
0.
#2150
b101 <
b101 "
b101 =
05
0$
14
1#
b10 6
b10 '
b10 ;
b1001 3
b10010000 2
b10010000 *
b101 0
b101 +
b101 1
1,
1.
