stack.v
`timescale 1ns/1ps

module stack(
    input [DATA_WIDTH-1:0] DATA_IN,
    input CLK,
    input nRW,
    input CE,
    input nRST,
    output reg [DATA_WIDTH-1:0] DATA_OUT,
    output reg FULL,
    output reg EMPTY
);

parameter DATA_WIDTH = 8;
parameter DEPTH = 3;

reg [DATA_WIDTH-1:0] STACK [0:(2**DEPTH)-1];
reg [DEPTH-1:0] SP;
reg [DATA_WIDTH-1:0] INDEX, NEXT_INDEX;
reg [DATA_WIDTH-1:0] NEXT_DATA_OUT;

always @(posedge CLK, negedge nRST) begin
    if(!nRST) begin
        DATA_OUT <= 8'b00000000;
        SP <= 3'b000;
        EMPTY <= 1'b1;
        FULL <= 1'b0;
    end else if(nRW == 1'b0 && CE == 1'b1) begin // read condition
        if (EMPTY) begin
            SP <= SP;
            EMPTY <= EMPTY;
        end else if (SP == 3'b000 && EMPTY == 1'b0) begin
            SP <= SP;
            DATA_OUT <= STACK[SP];
            EMPTY <= 1'b1;
        end else if (SP == 3'b111 && FULL == 1'b1) begin
            SP <= SP;
            DATA_OUT <= STACK[SP];
            EMPTY <= 1'b0;
            FULL <= 1'b0;
        end else begin
            SP <= SP - 1;
            DATA_OUT <= STACK[SP-1];
            EMPTY <= 1'b0;
            FULL <= 1'b0;
        end
    end else if(nRW == 1'b1 && CE == 1'b1) begin // write condition
        if (FULL) begin
            SP <= SP;
            FULL <= FULL;
        end else if (SP == 3'b111 && FULL == 1'b0) begin
            SP <= SP;
            STACK[SP] <= DATA_IN;
            FULL <= 1'b1;
        end else begin
            SP <= SP + 1;
            STACK[SP] <= DATA_IN;
            FULL <= 1'b0;
            EMPTY <= 1'b0;
        end
    end
end

endmodule // stack

tb_stack.v
`timescale 1ns/100ps
`include "stack.v"

module tb_stack();

parameter DATA_WIDTH = 8;
parameter DEPTH = 3;

reg [DATA_WIDTH-1:0] DATA_IN;
reg CLK;
reg nRW;
reg CE;
reg nRST;
wire [DATA_WIDTH-1:0] DATA_OUT;
wire FULL;
wire EMPTY;

stack stack(
    .DATA_IN(DATA_IN),
    .CLK(CLK),
    .nRW(nRW),
    .CE(CE),
    .nRST(nRST),
    .DATA_OUT(DATA_OUT),
    .FULL(FULL),
    .EMPTY(EMPTY)
);

initial begin
    #10 nRST = 1'b1;
    #10 DATA_IN = 8'h2A;
    CE = 1'b1;
    nRW = 1'b1;
    #10 CE = 1'b0;
    nRW = 1'b0;
    #10 CE = 1'b1;
    #10 CE = 1'b0;
    #10 DATA_IN = 8'h18;
    CE = 1'b1;
    nRW = 1'b1;
    #10 DATA_IN = 8'h16;
    #10 DATA_IN = 8'h44;
    #10 CE = 1'b0;
    #10 nRW = 1'b0;
    CE = 1'b1;
    #20 nRW = 1'b1;
    DATA_IN = 8'h15;
    #10 DATA_IN = 8'h15;
    #10 DATA_IN = 8'h21;
    #10 DATA_IN = 8'hFE;
    #10 DATA_IN = 8'hAC;
    #10 DATA_IN = 8'hAB;
    #10 DATA_IN = 8'h66;
    #10 DATA_IN = 8'h11;
    #10 CE = 1'b0;
    #10 nRW = 1'b0;
    CE = 1'b1;
    #50 CE = 1'b0;
    #10 DATA_IN = 8'h33;
    CE = 1'b1;
    nRW = 1'b1;
    #10 nRW = 1'b0;
    #40 CE = 1'b0;
    #10 nRW = 1'b1;
    DATA_IN = 8'h55;
    CE = 1'b1;
    #10 CE = 1'b0;
    #30 nRW = 1'b0;
    CE = 1'b1;
    #10 CE = 1'b0;
    #100 $finish;
end

initial begin
    CE = 1'b0;
    DATA_IN = 8'b00000000;
    nRST = 1'b0;
    CLK = 1'b0;
    forever #5 CLK = ~CLK;
end

initial begin
    $dumpfile("tb_stack.vcd");
    $dumpvars(0, tb_stack);
    $dumpon;
end

endmodule

tb_stack.vcd
$date
	Sun Dec 10 17:43:30 2023
$end
$version
	Icarus Verilog
$end
$timescale
	1ps
$end
$scope module tb_stack $end
$var wire 8 ! DATA_OUT [7:0] $end
$var wire 1 " EMPTY $end
$var wire 1 # FULL $end
$var reg 1 $ CE $end
$var reg 1 % CLK $end
$var reg 8 & DATA_IN [7:0] $end
$var reg 1 ' nRST $end
$var reg 1 ( nRW $end
$scope module stack $end
$var wire 1 ) CE $end
$var wire 1 * CLK $end
$var wire 8 + DATA_IN [7:0] $end
$var wire 1 , nRST $end
$var wire 1 - nRW $end
$var reg 8 . DATA_OUT [7:0] $end
$var reg 1 / EMPTY $end
$var reg 1 0 FULL $end
$var reg 3 1 SP [2:0] $end
$upscope $end
$upscope $end
$enddefinitions $end
#0
$dumpvars
b0 1
00
1/
b0 .
x-
0,
b0 +
0*
0)
x(
0'
b0 &
0%
0$
0#
1"
b0 !
$end
#5000
1%
1*
#10000
0%
0*
1'
1,
#15000
1%
1*
#20000
0%
0*
1(
1-
1$
1)
b101010 &
b101010 +
#25000
0/
0"
b1 1
1%
1*
#30000
0%
0*
0(
0-
0$
0)
#35000
1%
1*
#40000
0%
0*
1$
1)
#45000
b101010 .
b101010 !
b0 1
1%
1*
#50000
0%
0*
0$
0)
#55000
1%
1*
#60000
0%
0*
1(
1-
1$
1)
b11000 &
b11000 +
#65000
b1 1
1%
1*
#70000
0%
0*
b10110 &
b10110 +
#75000
b10 1
1%
1*
#80000
0%
0*
b1000100 &
b1000100 +
#85000
b11 1
1%
1*
#90000
0%
0*
0$
0)
#95000
1%
1*
#100000
0%
0*
1$
1)
0(
0-
#105000
b1000100 .
b1000100 !
b10 1
1%
1*
#110000
0%
0*
#115000
b10110 .
b10110 !
b1 1
1%
1*
#120000
0%
0*
b10101 &
b10101 +
1(
1-
#125000
b10 1
1%
1*
#130000
0%
0*
#135000
b11 1
1%
1*
#140000
0%
0*
b100001 &
b100001 +
#145000
b100 1
1%
1*
#150000
0%
0*
b11111110 &
b11111110 +
#155000
b101 1
1%
1*
#160000
0%
0*
b10101100 &
b10101100 +
#165000
b110 1
1%
1*
#170000
0%
0*
b10101011 &
b10101011 +
#175000
b111 1
1%
1*
#180000
0%
0*
b1100110 &
b1100110 +
#185000
10
1#
1%
1*
#190000
0%
0*
b10001 &
b10001 +
#195000
1%
1*
#200000
0%
0*
0$
0)
#205000
1%
1*
#210000
0%
0*
1$
1)
0(
0-
#215000
00
0#
b1100110 .
b1100110 !
1%
1*
#220000
0%
0*
#225000
b10101011 .
b10101011 !
b110 1
1%
1*
#230000
0%
0*
#235000
b10101100 .
b10101100 !
b101 1
1%
1*
#240000
0%
0*
#245000
b11111110 .
b11111110 !
b100 1
1%
1*
#250000
0%
0*
#255000
b100001 .
b100001 !
b11 1
1%
1*
#260000
0%
0*
0$
0)
#265000
1%
1*
#270000
0%
0*
1(
1-
1$
1)
b110011 &
b110011 +
#275000
b100 1
1%
1*
#280000
0%
0*
0(
0-
#285000
b110011 .
b110011 !
b11 1
1%
1*
#290000
0%
0*
#295000
b10101 .
b10101 !
b10 1
1%
1*
#300000
0%
0*
#305000
b1 1
1%
1*
#310000
0%
0*
#315000
b11000 .
b11000 !
b0 1
1%
1*
#320000
0%
0*
0$
0)
#325000
1%
1*
#330000
0%
0*
1$
1)
b1010101 &
b1010101 +
1(
1-
#335000
b1 1
1%
1*
#340000
0%
0*
0$
0)
#345000
1%
1*
#350000
0%
0*
#355000
1%
1*
#360000
0%
0*
#365000
1%
1*
#370000
0%
0*
1$
1)
0(
0-
#375000
b1010101 .
b1010101 !
b0 1
1%
1*
#380000
0%
0*
0$
0)
