register.v
// -------------------- REGISTERS --------------------
// only one

module register(
	input [WIDTH-1:0] IN,
	input CLK,
	input CE,
	// input RST,
	output reg [WIDTH-1:0] OUT
);

parameter WIDTH = 8;

always @(posedge CLK) begin
	// if(RST == 1'b1) OUT <= 1'b0; // needed for sim when there are none ldi instructions
	// else begin
		if(CE == 1'b0) OUT <= OUT;
		else OUT <= IN;
	// end
end

endmodule // register

ALU.v
module alu(
	input [DATA_WIDTH-1:0] IN0,
	input [DATA_WIDTH-1:0] IN1,
	input [OP_WIDTH-1:0] OP,
	output reg [DATA_WIDTH-1:0] OUT
);

parameter DATA_WIDTH = 8;
parameter OP_WIDTH = 4;

always @(*) begin
	case(OP)
		4'b0000: OUT <= ~IN0;			// NOT
		4'b0001: OUT <= IN0 ^ IN1;		// XOR
		4'b0010: OUT <= IN0 | IN1;		// OR
		4'b0011: OUT <= IN0 & IN1;		// AND
		4'b0100: OUT <= IN0 - IN1;		// SUB
		4'b0101: OUT <= IN0 + IN1;		// ADD
		4'b0110: OUT <= IN0 >> 1;		// RR
		4'b0111: OUT <= IN0 << 1;		// RL
		4'b1000: OUT <= IN0 - 1'b1;		// DEC
		4'b1001: OUT <= IN0 + 1'b1;		// INC
		4'b1010: OUT <= IN0;			// IN0
		4'b1011: OUT <= IN1;			// IN1
		default: OUT <= IN0;
	endcase
end

endmodule // alu

test_bench/tb_alu.v
`timescale 1ns/100ps

module tb_alu();

parameter DATA_WIDTH = 4;
parameter OP_WIDTH = 2;

reg [DATA_WIDTH-1:0] IN0;
wire [DATA_WIDTH-1:0] ALU_IN1;
reg [OP_WIDTH-1:0] OP;
wire [DATA_WIDTH-1:0] ALU_OUT;
wire [DATA_WIDTH-1:0] ACC_OUT;
reg CLK;
reg CE_ACC;
reg CE_R0;

alu alu1(
    .IN0(IN0),
    .IN1(ALU_IN1),
    .OP(OP),
    .OUT(ALU_OUT)
);

register ACC(
    .IN(ALU_OUT),
    .CLK(CLK),
    .CE(CE_ACC),
    .OUT(ACC_OUT)
);

register R0(
    .IN(ACC_OUT),
    .CLK(CLK),
    .CE(CE_R0),
    .OUT(ALU_IN1)
);

initial begin
    IN0 = 4'h0;
    OP = 2'b00;
    CE_ACC = 1'b0;
    CE_R0 = 1'b0;
    
    CLK = 1'b0;
    forever #5 CLK = ~CLK;
end

initial begin
    #10 IN0 = 4'hA;
    OP = 2'b01;
    CE_ACC = 1'b1; // loading value to ACC
    #10 OP = 2'b10;
    CE_ACC = 1'b1;
    #10 CE_ACC = 1'b0; // incrementing value in ACC
    #10 CE_R0 = 1'b1;
    #10 CE_R0 = 1'b0; // loading value to R0
    #10 OP = 2'b00;
    IN0 = 4'h2;
    CE_ACC = 1'b1;
    #10 CE_ACC = 1'b0; // adding R0(1010) and IN0(0020)
    #10 OP = 2'b11;
    CE_ACC = 1'b1;
    #10 CE_ACC = 1'b0; // loading value from R0

    #20 $finish;
end

initial begin
    $dumpfile("tb_alu.vcd");
    $dumpvars(0, tb_alu);
    $dumpon;
end

endmodule

test_bench/tb_alu.vcd
$date
	Sun Oct 29 21:11:46 2023
$end
$version
	Icarus Verilog
$end
$timescale
	100ps
$end
$scope module tb_alu $end
$var wire 4 ! ACC_OUT [3:0] $end
$var wire 4 " ALU_IN1 [3:0] $end
$var wire 4 # ALU_OUT [3:0] $end
$var reg 1 $ CE_ACC $end
$var reg 1 % CE_R0 $end
$var reg 1 & CLK $end
$var reg 4 ' IN0 [3:0] $end
$var reg 2 ( OP [1:0] $end
$scope module alu1 $end
$var wire 4 ) IN0 [3:0] $end
$var wire 4 * IN1 [3:0] $end
$var wire 2 + OP [1:0] $end
$var reg 4 , OUT [3:0] $end
$upscope $end
$scope module ACC $end
$var wire 1 - CE $end
$var wire 1 . CLK $end
$var wire 4 / IN [3:0] $end
$var reg 4 0 OUT [3:0] $end
$upscope $end
$scope module R0 $end
$var wire 1 1 CE $end
$var wire 1 . CLK $end
$var wire 4 2 IN [3:0] $end
$var reg 4 3 OUT [3:0] $end
$upscope $end
$upscope $end
$enddefinitions $end
#0
$dumpvars
bx 3
bx 2
01
bx 0
bx /
0.
0-
bx ,
b0 +
bx *
b0 )
b0 (
b0 '
0&
0%
0$
bx #
bx "
bx !
$end
#50
1&
1.
#100
b1010 ,
b1010 #
b1010 /
0&
0.
1$
1-
b1 (
b1 +
b1010 '
b1010 )
#150
b1010 0
b1010 !
b1010 2
1&
1.
#200
b1011 ,
b1011 #
b1011 /
0&
0.
b10 (
b10 +
#250
b1011 0
b1011 !
b1011 2
1&
1.
#300
0&
0.
0$
0-
#350
1&
1.
#400
0&
0.
1%
11
#450
b1011 3
b1011 "
b1011 *
1&
1.
#500
0&
0.
0%
01
#550
1&
1.
#600
b1101 ,
b1101 #
b1101 /
0&
0.
1$
1-
b10 '
b10 )
b0 (
b0 +
#650
b1101 0
b1101 !
b1101 2
1&
1.
#700
0&
0.
0$
0-
#750
1&
1.
#800
b1011 ,
b1011 #
b1011 /
0&
0.
1$
1-
b11 (
b11 +
#850
b1011 0
b1011 !
b1011 2
1&
1.
#900
0&
0.
0$
0-
