register.v
// -------------------- REGISTERS --------------------
// only one

`timescale 1ns/1ns

module register #(
	parameter DATA_WIDTH = 8) (
	input [DATA_WIDTH-1:0] IN,
	input CLK,
	input CE,
	input nRST,
	output reg [DATA_WIDTH-1:0] OUT
);

always @(posedge CLK or negedge nRST) begin
	// if(RST == 1'b1) OUT <= 1'b0; // needed for sim when there are none ldi instructions
	// else begin
		// if(CE == 1'b0) OUT <= OUT;
		// else OUT <= IN;
		if(!nRST) OUT <= 0;
		else if(CE) OUT <= IN;
	// end
end

endmodule // register

ALU.v
`timescale 1ns/1ns

module ALU #(
	parameter DATA_WIDTH = 8) (
	input [DATA_WIDTH-1:0] IN0,
	input [DATA_WIDTH-1:0] IN1,
	input [OP_WIDTH-1:0] OP,
	output reg ZF,
	output reg [DATA_WIDTH-1:0] OUT
);

parameter OP_WIDTH = 4;

always @(*) begin
	case(OP)
		4'b0000: OUT <= ~IN0;			// NOT
		4'b0001: OUT <= IN0 ^ IN1;		// XOR
		4'b0010: OUT <= IN0 | IN1;		// OR
		4'b0011: OUT <= IN0 & IN1;		// AND
		4'b0100: OUT <= IN0 - IN1;		// SUB
		4'b0101: OUT <= IN0 + IN1;		// ADD
		4'b0110: OUT <= IN0 >> 1;		// RR
		4'b0111: OUT <= IN0 << 1;		// RL
		4'b1000: OUT <= IN0 - 1'b1;		// DEC
		4'b1001: OUT <= IN0 + 1'b1;		// INC
		4'b1010: OUT <= IN0;			// IN0
		4'b1011: OUT <= IN1;			// IN1
		4'b1100: OUT <= ~(IN0 ^ IN1);	// XNOR
		default: OUT <= IN0;
	endcase
end

always @(OUT, OP) begin
	case(OP)
		4'b0000: ZF <= ~|OUT; // NOT
		4'b0001: ZF <= ~|OUT; // XOR
		4'b0010: ZF <= ~|OUT; // OR
		4'b0011: ZF <= ~|OUT; // AND
		4'b0100: ZF <= ~|OUT; // SUB
		4'b0101: ZF <= ~|OUT; // ADD
		4'b0110: ZF <= ~|OUT; // RR
		4'b0111: ZF <= ~|OUT; // RL
		4'b1000: ZF <= ~|OUT; // DEC
		4'b1001: ZF <= ~|OUT; // INC
		4'b1100: ZF <= ~|OUT; // XNOR
		default: ZF <= ZF;
	endcase
end

endmodule // ALU

test_bench/tb_alu.v
// `include "../ALU.v"
// `include "../register.v"
// `timescale 1ns/100ps

// module tb_alu();

// parameter DATA_WIDTH = 8;
// parameter OP_WIDTH = 4;

// reg [DATA_WIDTH-1:0] IN0;
// wire [DATA_WIDTH-1:0] ALU_IN1;
// reg [OP_WIDTH-1:0] OP;
// wire [DATA_WIDTH-1:0] ALU_OUT;
// wire [DATA_WIDTH-1:0] ACC_OUT;
// wire ZF;
// reg CLK;
// reg CE_ACC;
// reg CE_R0;

// ALU alu1(
//     .IN0(IN0),
//     .IN1(ALU_IN1),
//     .OP(OP),
//     .ZF(ZF),
//     .OUT(ALU_OUT)
// );

// register ACC(
//     .IN(ALU_OUT),
//     .CLK(CLK),
//     .CE(CE_ACC),
//     .OUT(ACC_OUT)
// );

// register R0(
//     .IN(ACC_OUT),
//     .CLK(CLK),
//     .CE(CE_R0),
//     .OUT(ALU_IN1)
// );

// initial begin
//     nRST = 1'b0;
//     IN0 = 8'h0;
//     OP = 4'b1010;
//     CE_ACC = 1'b0;
//     CE_R0 = 1'b0;
    
//     CLK = 1'b0;
//     forever #5 CLK = ~CLK;
// end

// initial begin
//     #10 nRST = 1'b1;
//     #10 IN0 = 8'hAA;
//     OP = 4'b1010;
//     CE_ACC = 1'b1; // loading value to ACC
//     #10 OP = 2'b0010;
//     CE_ACC = 1'b1;
//     #10 CE_ACC = 1'b0; // incrementing value in ACC
//     #10 CE_R0 = 1'b1;
//     #10 CE_R0 = 1'b0; // loading value to R0
//     #10 OP = 2'b00;
//     IN0 = 8'h2;
//     CE_ACC = 1'b1;
//     #10 CE_ACC = 1'b0; // adding R0(1010) and IN0(0020)
//     #10 OP = 2'b11;
//     CE_ACC = 1'b1;
//     #10 CE_ACC = 1'b0; // loading value from R0

//     #20 $finish;
// end

// initial begin
//     $dumpfile("tb_alu.vcd");
//     $dumpvars(0, tb_alu);
//     $dumpon;
// end

// endmodule

`include "../ALU.v"
`include "../register.v"
`timescale 1ns/100ps

module tb_alu();

parameter DATA_WIDTH = 8;
parameter OP_WIDTH = 4;

reg [DATA_WIDTH-1:0] IN0;
reg [DATA_WIDTH-1:0] IN1;
reg [OP_WIDTH-1:0] OP;
wire [DATA_WIDTH-1:0] OUT;
wire ZF;

ALU alu1(
    .IN0(IN0),
    .IN1(IN1),
    .OP(OP),
    .ZF(ZF),
    .OUT(OUT)
);

initial begin
    IN0 = 8'h0;
    IN1 = 8'h0;
    OP = 4'b1010;
    #20 IN0 = 8'h23;
    IN1 = 8'hDC;
    OP = 4'b0101;
    #20 IN0 = 8'h24;
    #20 IN0 = 8'hFF;
    #20 OP = 4'b0000;
    #20 OP = 4'b0011;
    #20 OP = 4'b1001;
    #20 IN0 = 8'h2A;
    OP = 4'b1010;
    #20 OP = 4'b0001;

    #20 $finish;
end

initial begin
    $dumpfile("tb_alu.vcd");
    $dumpvars(0, tb_alu);
    $dumpon;
end

endmodule

test_bench/tb_alu.vcd
$date
	Sat Jan 27 17:46:53 2024
$end
$version
	Icarus Verilog
$end
$timescale
	1ps
$end
$scope module tb_alu $end
$var wire 1 ! ZF $end
$var wire 8 " OUT [7:0] $end
$var reg 8 # IN0 [7:0] $end
$var reg 8 $ IN1 [7:0] $end
$var reg 4 % OP [3:0] $end
$scope module alu1 $end
$var wire 8 & IN0 [7:0] $end
$var wire 8 ' IN1 [7:0] $end
$var wire 4 ( OP [3:0] $end
$var reg 8 ) OUT [7:0] $end
$var reg 1 ! ZF $end
$upscope $end
$upscope $end
$enddefinitions $end
#0
$dumpvars
b0 )
b1010 (
b0 '
b0 &
b1010 %
b0 $
b0 #
b0 "
x!
$end
#20000
0!
b11111111 "
b11111111 )
b101 %
b101 (
b11011100 $
b11011100 '
b100011 #
b100011 &
#40000
1!
b0 "
b0 )
b100100 #
b100100 &
#60000
0!
b11011011 "
b11011011 )
b11111111 #
b11111111 &
#80000
1!
b0 "
b0 )
b0 %
b0 (
#100000
0!
b11011100 "
b11011100 )
b11 %
b11 (
#120000
1!
b0 "
b0 )
b1001 %
b1001 (
#140000
b101010 "
b101010 )
b1010 %
b1010 (
b101010 #
b101010 &
#160000
0!
b11110110 "
b11110110 )
b1 %
b1 (
