jump_conditions.v
`timescale 1ns/1ns

module jump_conditions (
    input [1:0] JUMP,
    input ZF,
    output CE_PC
);

assign CE_PC = ZF && JUMP[0] || ~ZF && JUMP[1];

/* Jump conditions:
JUMP =
        00  no jump
        01  JZ
        10  JNZ
        11  JMP (unconditional)
*/

endmodule // jump_conditions

test_bench/tb_jump_conditions.v
`include "../jump_conditions.v"
`timescale 1ns/1ps

module tb_jump_conditions();

reg [1:0] JUMP;
reg ZF;
wire CE_PC;

jump_conditions jmp(
    .JUMP(JUMP),
    .ZF(ZF),
    .CE_PC(CE_PC)
);

initial begin
    JUMP = 2'b00;
    ZF = 1'b0;
    #20 JUMP = 2'b01;
    #20 JUMP = 2'b10;
    #20 JUMP = 2'b11;
    #20 ZF = 1'b1;
    #20 JUMP = 2'b00;
    #20 JUMP = 2'b01;
    #20 JUMP = 2'b10;
    #20 JUMP = 2'b11;
    #20 $finish;
end

initial begin
    $dumpfile("tb_jump_conditions.vcd");
    $dumpvars(0, tb_jump_conditions);
    $dumpon;
end

endmodule // tb_jump_conditions

test_bench/tb_jump_conditions.vcd
$date
	Sat Jan 27 17:24:34 2024
$end
$version
	Icarus Verilog
$end
$timescale
	1ps
$end
$scope module tb_jump_conditions $end
$var wire 1 ! CE_PC $end
$var reg 2 " JUMP [1:0] $end
$var reg 1 # ZF $end
$scope module jmp $end
$var wire 1 ! CE_PC $end
$var wire 2 $ JUMP [1:0] $end
$var wire 1 # ZF $end
$upscope $end
$upscope $end
$enddefinitions $end
#0
$dumpvars
b0 $
0#
b0 "
0!
$end
#20000
b1 "
b1 $
#40000
1!
b10 "
b10 $
#60000
b11 "
b11 $
#80000
1#
#100000
0!
b0 "
b0 $
#120000
1!
b1 "
b1 $
#140000
0!
b10 "
b10 $
#160000
1!
b11 "
b11 $
