ram_mem.v
module ram_mem(
    input CLK,
    input CE,
    input [ADDR_WIDTH-1:0] ADDR,
	input [WIDTH-1:0] DATA_IN,
	output reg [WIDTH-1:0] DATA_OUT
);

parameter ADDR_WIDTH = 4;
parameter WIDTH = 8;

reg [WIDTH-1:0] MEM [0:(2**ADDR_WIDTH)-1];

always @(posedge CLK) begin
    if(CE) MEM[ADDR] <= DATA_IN;
    DATA_OUT <= MEM[ADDR];
end

// initial begin
//     $readmemb("ram_test.mem", MEM);
// end

endmodule // ram_mem

test_bench/tb_ram_mem.v
`timescale 1ns/1ps
`include "ram_mem.v"

module tb_ram_mem();

reg CLK;
reg [7:0] DATA_IN;
reg [3:0] ADDR;
reg CE;
wire [7:0] DATA_OUT;

ram_mem RAM(
    .CLK(CLK),
    .DATA_IN(DATA_IN),
    .ADDR(ADDR),
    .CE(CE),
    .DATA_OUT(DATA_OUT)
);

initial begin
    CLK = 1'b0;
    forever #5 CLK = ~CLK;
end

initial begin
    DATA_IN = 8'b00000000;
    ADDR = 4'b0000;
    CE = 1'b0;

    #10 DATA_IN = 8'b00101011;
    ADDR = 4'b1010;
    CE = 1'b1;
    
    #10 CE = 1'b0;
    ADDR = 4'b1011;

    #10 DATA_IN = 8'b11011010;
    CE = 1'b1;

    #10 CE = 1'b0;
    ADDR = 4'b1010;

    #10 ADDR = 4'b1011;

    #10 $finish;
end

initial begin
    $dumpfile("tb_ram_mem.vcd");
    $dumpvars(0, tb_ram_mem);
    $dumpon;
end

endmodule

test_bench/tb_ram_mem.vcd
$date
	Mon Nov 13 11:08:34 2023
$end
$version
	Icarus Verilog
$end
$timescale
	1ps
$end
$scope module tb_ram_mem $end
$var wire 8 ! DATA_OUT [7:0] $end
$var reg 4 " ADDR [3:0] $end
$var reg 1 # CE $end
$var reg 1 $ CLK $end
$var reg 8 % DATA_IN [7:0] $end
$scope module RAM $end
$var wire 4 & ADDR [3:0] $end
$var wire 1 # CE $end
$var wire 1 $ CLK $end
$var wire 8 ' DATA_IN [7:0] $end
$var reg 8 ( DATA_OUT [7:0] $end
$upscope $end
$upscope $end
$enddefinitions $end
#0
$dumpvars
bx (
b0 '
b0 &
b0 %
0$
0#
b0 "
bx !
$end
#5000
1$
#10000
0$
1#
b1010 "
b1010 &
b101011 %
b101011 '
#15000
1$
#20000
0$
b1011 "
b1011 &
0#
#25000
1$
#30000
0$
1#
b11011010 %
b11011010 '
#35000
1$
#40000
0$
b1010 "
b1010 &
0#
#45000
b101011 !
b101011 (
1$
#50000
0$
b1011 "
b1011 &
#55000
b11011010 !
b11011010 (
1$
