rom16x8.v
// -------------------- ROM --------------------
// 16 cells of f8 bit DATA

module rom16x8(
	input [ADDR_WIDTH-1:0] ADDR,
	output reg [WIDTH-1:0] DATA
);

parameter WIDTH = 12;
parameter ADDR_WIDTH = 4;

always @(*) begin
	case(ADDR)
		4'h0: DATA <= 12'hC00; // nop				0	0
		4'h1: DATA <= 12'hD20; // ldi 2			1	0
		// 4'h1: DATA <= 12'h900; // inc A			1	0
		4'h2: DATA <= 12'h900; // inc A			2	0
		4'h3: DATA <= 12'h900; // inc A			3	0
		4'h4: DATA <= 12'hB00; // ST R			3	3
		4'h5: DATA <= 12'h900; // inc A			4	3
		4'h6: DATA <= 12'h900; // inc A			5	3
		4'h7: DATA <= 12'h500; // add R			8	3
		4'h8: DATA <= 12'h900; // inc A			9	3
		4'h9: DATA <= 12'h900; // inc A			A	3
		4'hA: DATA <= 12'hA00; // LD R			3	3
		4'hB: DATA <= 12'h500; // add R			6	3
		4'hC: DATA <= 12'h900; // inc A			7	3
		4'hD: DATA <= 12'h900; // inc A			8	3
		4'hE: DATA <= 12'hE00; // rst				8	3
		4'hF: DATA <= 12'hC00;
	endcase
end

endmodule // rom16x8

program_counter.v
// -------------------- COUNTER --------------------
// counter module of WIDTH bits width

module program_counter(
	input RST,
	input CLK,
	output reg [WIDTH-1:0] DATA
);

parameter WIDTH = 4;

always @(posedge CLK) begin
	if(RST == 1) DATA <= 4'h0;
	else DATA <= DATA + 1;
end

endmodule // program_counter

test_bench/tb_rom.v
`timescale 1ns/1ps

module tb_rom();

reg CLK;
reg RST;
wire [3:0] ADDR;
wire [7:0] DATA;

program_counter p1(
    .CLK(CLK),
    .RST(RST),
    .DATA(ADDR)
);

rom16x8 rom1(
    .ADDR(ADDR),
    .DATA(DATA)
);

initial begin
    CLK = 1'b0;
    forever #5 CLK <= ~CLK;
end

initial begin
    RST <= 1'b1;
    #20 RST <= 1'b0;
end

initial #200 $finish;

initial begin
    $dumpfile("tb_rom.vcd");
    $dumpvars(0, tb_rom);
    $dumpon;
end

endmodule

test_bench/tb_rom.vcd
$date
	Sun Oct 29 19:40:56 2023
$end
$version
	Icarus Verilog
$end
$timescale
	1ps
$end
$scope module tb_rom $end
$var wire 4 ! ADDR [3:0] $end
$var wire 8 " DATA [7:0] $end
$var reg 1 # CLK $end
$var reg 1 $ RST $end
$scope module p1 $end
$var wire 1 % CLK $end
$var wire 1 & RST $end
$var reg 4 ' DATA [3:0] $end
$upscope $end
$scope module rom1 $end
$var wire 4 ( ADDR [3:0] $end
$var reg 8 ) DATA [7:0] $end
$upscope $end
$upscope $end
$enddefinitions $end
#0
$dumpvars
bx )
bx (
bx '
1&
0%
1$
0#
bx "
bx !
$end
#5000
b11000000 )
b11000000 "
b0 '
b0 !
b0 (
1#
1%
#10000
0#
0%
#15000
1#
1%
#20000
0#
0%
0$
0&
#25000
b11010101 )
b11010101 "
b1 '
b1 !
b1 (
1#
1%
#30000
0#
0%
#35000
b10010000 )
b10010000 "
b10 '
b10 !
b10 (
1#
1%
#40000
0#
0%
#45000
b11 '
b11 !
b11 (
1#
1%
#50000
0#
0%
#55000
b10110000 )
b10110000 "
b100 '
b100 !
b100 (
1#
1%
#60000
0#
0%
#65000
b10010000 )
b10010000 "
b101 '
b101 !
b101 (
1#
1%
#70000
0#
0%
#75000
b110 '
b110 !
b110 (
1#
1%
#80000
0#
0%
#85000
b1010000 )
b1010000 "
b111 '
b111 !
b111 (
1#
1%
#90000
0#
0%
#95000
b10010000 )
b10010000 "
b1000 '
b1000 !
b1000 (
1#
1%
#100000
0#
0%
#105000
b1001 '
b1001 !
b1001 (
1#
1%
#110000
0#
0%
#115000
b10100000 )
b10100000 "
b1010 '
b1010 !
b1010 (
1#
1%
#120000
0#
0%
#125000
b1010000 )
b1010000 "
b1011 '
b1011 !
b1011 (
1#
1%
#130000
0#
0%
#135000
b10010000 )
b10010000 "
b1100 '
b1100 !
b1100 (
1#
1%
#140000
0#
0%
#145000
b1101 '
b1101 !
b1101 (
1#
1%
#150000
0#
0%
#155000
b11100000 )
b11100000 "
b1110 '
b1110 !
b1110 (
1#
1%
#160000
0#
0%
#165000
b11000000 )
b11000000 "
b1111 '
b1111 !
b1111 (
1#
1%
#170000
0#
0%
#175000
b0 '
b0 !
b0 (
1#
1%
#180000
0#
0%
#185000
b11010101 )
b11010101 "
b1 '
b1 !
b1 (
1#
1%
#190000
0#
0%
#195000
b10010000 )
b10010000 "
b10 '
b10 !
b10 (
1#
1%
